CHANGES.txt
LICENSE.txt
MANIFEST.in
README.txt
setup.cfg
setup.py
pySiesta.egg-info/PKG-INFO
pySiesta.egg-info/SOURCES.txt
pySiesta.egg-info/dependency_links.txt
pySiesta.egg-info/requires.txt
pySiesta.egg-info/top_level.txt
pysiesta/__init__.py
pysiesta/base.py
pysiesta/bm_eos.py
pysiesta/inputgroup.py
pysiesta/keys.py
pysiesta/main.py
pysiesta/stretch.py
pysiesta/test.py
pysiesta/vmd.py
test/test_sObj.py