Metadata-Version: 1.1
Name: pySiesta
Version: 0.1.1
Summary: Python wrapper for the DFT code SIESTA.
Home-page: UNKNOWN
Author: M. Ezequiel Castillo
Author-email: ezecastillo@gmail.com
License: GPLv3
Keywords: siesta dft electronic ab-initio molecules
Platform: UNKNOWN
Classifier: Development Status :: 3 - Alpha
Classifier: Programming Language :: Python :: 2.7
